{
  "vehicleId": "44865715",
  "vehicleName": "ABQ-VAN-01",
  "month": "2025_02",
  "pagination": {
    "endCursor": "trip_44865715_20250228_004",
    "hasNextPage": false
  },
  "trips": [
    {
      "id": "trip_44865715_20250201_001",
      "vehicleId": "44865715",
      "driverId": "20000045",
      "startMs": 1738398420000,
      "endMs": 1738407937139,
      "startAddress": "27730 Evans Squares Apt. 999",
      "endAddress": "1905 David Garden",
      "startCoords": {
        "latitude": 35.069159,
        "longitude": -106.632589
      },
      "endCoords": {
        "latitude": 35.08931,
        "longitude": -106.537744
      },
      "distanceMeters": 49972.3,
      "durationMs": 9517140,
      "drivingDurationMs": 8866410,
      "idlingDurationMs": 650730,
      "fuelConsumedMl": 6352,
      "fuelConsumedGallons": 1.678,
      "maxSpeedMph": 70.9,
      "averageSpeedMph": 11.7,
      "safetyEvents": [
        {
          "type": "speeding",
          "startMs": 1738405380000,
          "maxSpeedMph": 70.9
        }
      ]
    },
    {
      "id": "trip_44865715_20250201_002",
      "vehicleId": "44865715",
      "driverId": "20000045",
      "startMs": 1738428000000,
      "endMs": 1738437884689,
      "startAddress": "974 Andrew Cape Suite 318",
      "endAddress": "00908 Thomas Key",
      "startCoords": {
        "latitude": 35.124084,
        "longitude": -106.539764
      },
      "endCoords": {
        "latitude": 35.049433,
        "longitude": -106.561096
      },
      "distanceMeters": 72964.4,
      "durationMs": 9884689,
      "drivingDurationMs": 8719575,
      "idlingDurationMs": 1165114,
      "fuelConsumedMl": 9278,
      "fuelConsumedGallons": 2.451,
      "maxSpeedMph": 43.0,
      "averageSpeedMph": 16.5,
      "safetyEvents": []
    },
    {
      "id": "trip_44865715_20250202_001",
      "vehicleId": "44865715",
      "driverId": "20000046",
      "startMs": 1738481880000,
      "endMs": 1738485433822,
      "startAddress": "770 Rogers Avenue Suite 985",
      "endAddress": "81452 Perez Cliffs Apt. 438",
      "startCoords": {
        "latitude": 35.071864,
        "longitude": -106.660552
      },
      "endCoords": {
        "latitude": 35.117736,
        "longitude": -106.716575
      },
      "distanceMeters": 26928.5,
      "durationMs": 3553823,
      "drivingDurationMs": 3359389,
      "idlingDurationMs": 194434,
      "fuelConsumedMl": 3422,
      "fuelConsumedGallons": 0.904,
      "maxSpeedMph": 40.1,
      "averageSpeedMph": 16.9,
      "safetyEvents": []
    },
    {
      "id": "trip_44865715_20250202_002",
      "vehicleId": "44865715",
      "driverId": "20000046",
      "startMs": 1738478820000,
      "endMs": 1738491004147,
      "startAddress": "454 Clinton Meadow",
      "endAddress": "6816 Paul Forges Apt. 265",
      "startCoords": {
        "latitude": 35.051915,
        "longitude": -106.704756
      },
      "endCoords": {
        "latitude": 35.056357,
        "longitude": -106.698705
      },
      "distanceMeters": 56030.4,
      "durationMs": 12184148,
      "drivingDurationMs": 10148079,
      "idlingDurationMs": 2036068,
      "fuelConsumedMl": 7124,
      "fuelConsumedGallons": 1.882,
      "maxSpeedMph": 70.0,
      "averageSpeedMph": 10.3,
      "safetyEvents": [
        {
          "type": "speeding",
          "startMs": 1738481700000,
          "maxSpeedMph": 70.0
        }
      ]
    },
    {
      "id": "trip_44865715_20250202_003",
      "vehicleId": "44865715",
      "driverId": "20000046",
      "startMs": 1738508520000,
      "endMs": 1738523368519,
      "startAddress": "525 Dawn Estate Suite 011",
      "endAddress": "1487 Claudia Via",
      "startCoords": {
        "latitude": 35.122534,
        "longitude": -106.687026
      },
      "endCoords": {
        "latitude": 35.094761,
        "longitude": -106.604839
      },
      "distanceMeters": 83240.5,
      "durationMs": 14848520,
      "drivingDurationMs": 13112762,
      "idlingDurationMs": 1735758,
      "fuelConsumedMl": 10584,
      "fuelConsumedGallons": 2.796,
      "maxSpeedMph": 60.1,
      "averageSpeedMph": 12.5,
      "safetyEvents": []
    },
    {
      "id": "trip_44865715_20250202_004",
      "vehicleId": "44865715",
      "driverId": "20000046",
      "startMs": 1738484640000,
      "endMs": 1738492086188,
      "startAddress": "618 Scott Neck Suite 988",
      "endAddress": "2231 Karen Port Apt. 675",
      "startCoords": {
        "latitude": 35.081875,
        "longitude": -106.675873
      },
      "endCoords": {
        "latitude": 35.042389,
        "longitude": -106.627516
      },
      "distanceMeters": 55413.5,
      "durationMs": 7446188,
      "drivingDurationMs": 6939057,
      "idlingDurationMs": 507131,
      "fuelConsumedMl": 7045,
      "fuelConsumedGallons": 1.861,
      "maxSpeedMph": 62.1,
      "averageSpeedMph": 16.6,
      "safetyEvents": []
    },
    {
      "id": "trip_44865715_20250203_001",
      "vehicleId": "44865715",
      "driverId": "20000046",
      "startMs": 1738563120000,
      "endMs": 1738566819737,
      "startAddress": "42710 Williams Cape",
      "endAddress": "71356 Tracy Hill Apt. 431",
      "startCoords": {
        "latitude": 35.179229,
        "longitude": -106.593
      },
      "endCoords": {
        "latitude": 35.082238,
        "longitude": -106.679608
      },
      "distanceMeters": 27734.4,
      "durationMs": 3699737,
      "drivingDurationMs": 3448267,
      "idlingDurationMs": 251470,
      "fuelConsumedMl": 3528,
      "fuelConsumedGallons": 0.932,
      "maxSpeedMph": 63.2,
      "averageSpeedMph": 16.8,
      "safetyEvents": []
    },
    {
      "id": "trip_44865715_20250203_002",
      "vehicleId": "44865715",
      "driverId": "20000046",
      "startMs": 1738582080000,
      "endMs": 1738588556180,
      "startAddress": "25404 Cristina Lights Suite 112",
      "endAddress": "701 Moran Extensions",
      "startCoords": {
        "latitude": 35.050446,
        "longitude": -106.640621
      },
      "endCoords": {
        "latitude": 35.084521,
        "longitude": -106.646751
      },
      "distanceMeters": 29959.6,
      "durationMs": 6476181,
      "drivingDurationMs": 5857416,
      "idlingDurationMs": 618765,
      "fuelConsumedMl": 3808,
      "fuelConsumedGallons": 1.006,
      "maxSpeedMph": 41.2,
      "averageSpeedMph": 10.3,
      "safetyEvents": []
    },
    {
      "id": "trip_44865715_20250203_003",
      "vehicleId": "44865715",
      "driverId": "20000046",
      "startMs": 1738593360000,
      "endMs": 1738603966472,
      "startAddress": "40677 Angela Island Suite 381",
      "endAddress": "507 Mcgee Canyon",
      "startCoords": {
        "latitude": 35.123075,
        "longitude": -106.680112
      },
      "endCoords": {
        "latitude": 35.155183,
        "longitude": -106.546983
      },
      "distanceMeters": 60245.5,
      "durationMs": 10606472,
      "drivingDurationMs": 10069811,
      "idlingDurationMs": 536661,
      "fuelConsumedMl": 7662,
      "fuelConsumedGallons": 2.024,
      "maxSpeedMph": 59.4,
      "averageSpeedMph": 12.7,
      "safetyEvents": []
    },
    {
      "id": "trip_44865715_20250203_004",
      "vehicleId": "44865715",
      "driverId": "20000046",
      "startMs": 1738567200000,
      "endMs": 1738579183087,
      "startAddress": "1896 Anderson Manors",
      "endAddress": "04763 Colleen Island Apt. 407",
      "startCoords": {
        "latitude": 35.178803,
        "longitude": -106.605087
      },
      "endCoords": {
        "latitude": 35.094348,
        "longitude": -106.676572
      },
      "distanceMeters": 78628.9,
      "durationMs": 11983087,
      "drivingDurationMs": 10748894,
      "idlingDurationMs": 1234193,
      "fuelConsumedMl": 9997,
      "fuelConsumedGallons": 2.641,
      "maxSpeedMph": 53.8,
      "averageSpeedMph": 14.7,
      "safetyEvents": []
    },
    {
      "id": "trip_44865715_20250203_005",
      "vehicleId": "44865715",
      "driverId": "20000046",
      "startMs": 1738564680000,
      "endMs": 1738568353438,
      "startAddress": "6131 Thomas Walk Suite 326",
      "endAddress": "34292 Miller Ramp",
      "startCoords": {
        "latitude": 35.054489,
        "longitude": -106.552508
      },
      "endCoords": {
        "latitude": 35.059372,
        "longitude": -106.639119
      },
      "distanceMeters": 16977.5,
      "durationMs": 3673439,
      "drivingDurationMs": 3025004,
      "idlingDurationMs": 648435,
      "fuelConsumedMl": 2158,
      "fuelConsumedGallons": 0.57,
      "maxSpeedMph": 50.5,
      "averageSpeedMph": 10.3,
      "safetyEvents": []
    },
    {
      "id": "trip_44865715_20250204_001",
      "vehicleId": "44865715",
      "driverId": "20000044",
      "startMs": 1738661040000,
      "endMs": 1738667347567,
      "startAddress": "8556 Keith Extension",
      "endAddress": "3340 Castaneda Forge",
      "startCoords": {
        "latitude": 35.07791,
        "longitude": -106.717831
      },
      "endCoords": {
        "latitude": 35.116849,
        "longitude": -106.632038
      },
      "distanceMeters": 40416.6,
      "durationMs": 6307567,
      "drivingDurationMs": 5684323,
      "idlingDurationMs": 623244,
      "fuelConsumedMl": 5137,
      "fuelConsumedGallons": 1.357,
      "maxSpeedMph": 52.2,
      "averageSpeedMph": 14.3,
      "safetyEvents": []
    },
    {
      "id": "trip_44865715_20250204_002",
      "vehicleId": "44865715",
      "driverId": "20000044",
      "startMs": 1738677960000,
      "endMs": 1738681467973,
      "startAddress": "839 Mark Spring",
      "endAddress": "550 Jamie Spring Apt. 302",
      "startCoords": {
        "latitude": 35.053506,
        "longitude": -106.591298
      },
      "endCoords": {
        "latitude": 35.052713,
        "longitude": -106.647228
      },
      "distanceMeters": 21758.8,
      "durationMs": 3507973,
      "drivingDurationMs": 2852512,
      "idlingDurationMs": 655461,
      "fuelConsumedMl": 2767,
      "fuelConsumedGallons": 0.731,
      "maxSpeedMph": 61.0,
      "averageSpeedMph": 13.9,
      "safetyEvents": []
    },
    {
      "id": "trip_44865715_20250204_003",
      "vehicleId": "44865715",
      "driverId": "20000044",
      "startMs": 1738690260000,
      "endMs": 1738701369100,
      "startAddress": "94968 Morris Station Suite 126",
      "endAddress": "01503 Joseph Coves Suite 395",
      "startCoords": {
        "latitude": 35.162186,
        "longitude": -106.676979
      },
      "endCoords": {
        "latitude": 35.073535,
        "longitude": -106.652798
      },
      "distanceMeters": 67148.8,
      "durationMs": 11109100,
      "drivingDurationMs": 10258668,
      "idlingDurationMs": 850432,
      "fuelConsumedMl": 8536,
      "fuelConsumedGallons": 2.255,
      "maxSpeedMph": 41.9,
      "averageSpeedMph": 13.5,
      "safetyEvents": []
    },
    {
      "id": "trip_44865715_20250204_004",
      "vehicleId": "44865715",
      "driverId": "20000044",
      "startMs": 1738661580000,
      "endMs": 1738668106137,
      "startAddress": "95987 Misty Island Apt. 622",
      "endAddress": "63171 Barnett Village",
      "startCoords": {
        "latitude": 35.102796,
        "longitude": -106.536812
      },
      "endCoords": {
        "latitude": 35.172784,
        "longitude": -106.557419
      },
      "distanceMeters": 46253.1,
      "durationMs": 6526137,
      "drivingDurationMs": 5442817,
      "idlingDurationMs": 1083320,
      "fuelConsumedMl": 5883,
      "fuelConsumedGallons": 1.554,
      "maxSpeedMph": 67.8,
      "averageSpeedMph": 15.9,
      "safetyEvents": [
        {
          "type": "speeding",
          "startMs": 1738666140000,
          "maxSpeedMph": 67.8
        }
      ]
    },
    {
      "id": "trip_44865715_20250204_005",
      "vehicleId": "44865715",
      "driverId": "20000044",
      "startMs": 1738675860000,
      "endMs": 1738683886310,
      "startAddress": "8762 Skinner Roads Suite 768",
      "endAddress": "7567 Jillian Ramp Suite 890",
      "startCoords": {
        "latitude": 35.151615,
        "longitude": -106.664964
      },
      "endCoords": {
        "latitude": 35.047138,
        "longitude": -106.567536
      },
      "distanceMeters": 41483.2,
      "durationMs": 8026311,
      "drivingDurationMs": 7009102,
      "idlingDurationMs": 1017208,
      "fuelConsumedMl": 5273,
      "fuelConsumedGallons": 1.393,
      "maxSpeedMph": 41.7,
      "averageSpeedMph": 11.6,
      "safetyEvents": []
    },
    {
      "id": "trip_44865715_20250204_006",
      "vehicleId": "44865715",
      "driverId": "20000044",
      "startMs": 1738651200000,
      "endMs": 1738653841967,
      "startAddress": "3374 Harris Plaza",
      "endAddress": "0380 Chad Port",
      "startCoords": {
        "latitude": 35.163794,
        "longitude": -106.576283
      },
      "endCoords": {
        "latitude": 35.094241,
        "longitude": -106.677906
      },
      "distanceMeters": 16196.2,
      "durationMs": 2641968,
      "drivingDurationMs": 2423934,
      "idlingDurationMs": 218034,
      "fuelConsumedMl": 2059,
      "fuelConsumedGallons": 0.544,
      "maxSpeedMph": 30.4,
      "averageSpeedMph": 13.7,
      "safetyEvents": []
    },
    {
      "id": "trip_44865715_20250205_001",
      "vehicleId": "44865715",
      "driverId": "20000044",
      "startMs": 1738761540000,
      "endMs": 1738769011145,
      "startAddress": "2459 Danielle Way",
      "endAddress": "71416 Gibson Square",
      "startCoords": {
        "latitude": 35.056937,
        "longitude": -106.629879
      },
      "endCoords": {
        "latitude": 35.073306,
        "longitude": -106.56397
      },
      "distanceMeters": 45834.7,
      "durationMs": 7471146,
      "drivingDurationMs": 7102823,
      "idlingDurationMs": 368322,
      "fuelConsumedMl": 5826,
      "fuelConsumedGallons": 1.539,
      "maxSpeedMph": 58.2,
      "averageSpeedMph": 13.7,
      "safetyEvents": []
    },
    {
      "id": "trip_44865715_20250205_002",
      "vehicleId": "44865715",
      "driverId": "20000044",
      "startMs": 1738778580000,
      "endMs": 1738787545414,
      "startAddress": "61827 Snyder Forest Apt. 948",
      "endAddress": "845 Helen Crest Apt. 058",
      "startCoords": {
        "latitude": 35.083909,
        "longitude": -106.545977
      },
      "endCoords": {
        "latitude": 35.170876,
        "longitude": -106.567568
      },
      "distanceMeters": 55275.5,
      "durationMs": 8965414,
      "drivingDurationMs": 8351401,
      "idlingDurationMs": 614014,
      "fuelConsumedMl": 7030,
      "fuelConsumedGallons": 1.857,
      "maxSpeedMph": 33.5,
      "averageSpeedMph": 13.8,
      "safetyEvents": []
    },
    {
      "id": "trip_44865715_20250205_003",
      "vehicleId": "44865715",
      "driverId": "20000044",
      "startMs": 1738762200000,
      "endMs": 1738764837589,
      "startAddress": "806 Brown Turnpike",
      "endAddress": "096 Jason Camp",
      "startCoords": {
        "latitude": 35.175145,
        "longitude": -106.711438
      },
      "endCoords": {
        "latitude": 35.096433,
        "longitude": -106.537359
      },
      "distanceMeters": 13950.0,
      "durationMs": 2637590,
      "drivingDurationMs": 2133560,
      "idlingDurationMs": 504030,
      "fuelConsumedMl": 1775,
      "fuelConsumedGallons": 0.469,
      "maxSpeedMph": 47.1,
      "averageSpeedMph": 11.8,
      "safetyEvents": []
    },
    {
      "id": "trip_44865715_20250205_004",
      "vehicleId": "44865715",
      "driverId": "20000044",
      "startMs": 1738736700000,
      "endMs": 1738741520804,
      "startAddress": "06345 Jonathan Hollow",
      "endAddress": "8232 Goodwin Land",
      "startCoords": {
        "latitude": 35.113896,
        "longitude": -106.600947
      },
      "endCoords": {
        "latitude": 35.151771,
        "longitude": -106.573108
      },
      "distanceMeters": 26318.7,
      "durationMs": 4820804,
      "drivingDurationMs": 4167295,
      "idlingDurationMs": 653509,
      "fuelConsumedMl": 3346,
      "fuelConsumedGallons": 0.884,
      "maxSpeedMph": 57.9,
      "averageSpeedMph": 12.2,
      "safetyEvents": []
    },
    {
      "id": "trip_44865715_20250205_005",
      "vehicleId": "44865715",
      "driverId": "20000044",
      "startMs": 1738752120000,
      "endMs": 1738755215879,
      "startAddress": "2440 Cook Pass Suite 478",
      "endAddress": "37039 Anthony Square",
      "startCoords": {
        "latitude": 35.112106,
        "longitude": -106.669063
      },
      "endCoords": {
        "latitude": 35.08946,
        "longitude": -106.62941
      },
      "distanceMeters": 15893.7,
      "durationMs": 3095879,
      "drivingDurationMs": 2512034,
      "idlingDurationMs": 583846,
      "fuelConsumedMl": 2021,
      "fuelConsumedGallons": 0.534,
      "maxSpeedMph": 60.3,
      "averageSpeedMph": 11.5,
      "safetyEvents": []
    },
    {
      "id": "trip_44865715_20250206_001",
      "vehicleId": "44865715",
      "driverId": "20000045",
      "startMs": 1738824480000,
      "endMs": 1738838758356,
      "startAddress": "1574 Lisa Manor Apt. 419",
      "endAddress": "52104 Huang Locks",
      "startCoords": {
        "latitude": 35.181695,
        "longitude": -106.568557
      },
      "endCoords": {
        "latitude": 35.178866,
        "longitude": -106.640423
      },
      "distanceMeters": 69783.6,
      "durationMs": 14278357,
      "drivingDurationMs": 11724344,
      "idlingDurationMs": 2554013,
      "fuelConsumedMl": 8873,
      "fuelConsumedGallons": 2.344,
      "maxSpeedMph": 41.1,
      "averageSpeedMph": 10.9,
      "safetyEvents": []
    },
    {
      "id": "trip_44865715_20250206_002",
      "vehicleId": "44865715",
      "driverId": "20000045",
      "startMs": 1738858860000,
      "endMs": 1738863031231,
      "startAddress": "458 Steve Extension Suite 572",
      "endAddress": "5820 Kelly Brooks",
      "startCoords": {
        "latitude": 35.166841,
        "longitude": -106.602579
      },
      "endCoords": {
        "latitude": 35.112383,
        "longitude": -106.551499
      },
      "distanceMeters": 22805.2,
      "durationMs": 4171232,
      "drivingDurationMs": 3753204,
      "idlingDurationMs": 418028,
      "fuelConsumedMl": 2900,
      "fuelConsumedGallons": 0.766,
      "maxSpeedMph": 48.5,
      "averageSpeedMph": 12.2,
      "safetyEvents": []
    },
    {
      "id": "trip_44865715_20250206_003",
      "vehicleId": "44865715",
      "driverId": "20000045",
      "startMs": 1738861140000,
      "endMs": 1738862572540,
      "startAddress": "635 Kenneth Pass",
      "endAddress": "737 Aaron Knolls",
      "startCoords": {
        "latitude": 35.081738,
        "longitude": -106.588394
      },
      "endCoords": {
        "latitude": 35.179719,
        "longitude": -106.663935
      },
      "distanceMeters": 10054.3,
      "durationMs": 1432541,
      "drivingDurationMs": 1161201,
      "idlingDurationMs": 271340,
      "fuelConsumedMl": 1279,
      "fuelConsumedGallons": 0.338,
      "maxSpeedMph": 38.7,
      "averageSpeedMph": 15.7,
      "safetyEvents": []
    },
    {
      "id": "trip_44865715_20250206_004",
      "vehicleId": "44865715",
      "driverId": "20000045",
      "startMs": 1738853940000,
      "endMs": 1738864942345,
      "startAddress": "374 Brooks Parks",
      "endAddress": "941 Smith Tunnel Apt. 655",
      "startCoords": {
        "latitude": 35.168987,
        "longitude": -106.550055
      },
      "endCoords": {
        "latitude": 35.14101,
        "longitude": -106.651732
      },
      "distanceMeters": 57457.0,
      "durationMs": 11002346,
      "drivingDurationMs": 9018100,
      "idlingDurationMs": 1984246,
      "fuelConsumedMl": 7306,
      "fuelConsumedGallons": 1.93,
      "maxSpeedMph": 33.6,
      "averageSpeedMph": 11.7,
      "safetyEvents": []
    },
    {
      "id": "trip_44865715_20250206_005",
      "vehicleId": "44865715",
      "driverId": "20000045",
      "startMs": 1738846020000,
      "endMs": 1738856151823,
      "startAddress": "3455 Angela Isle Apt. 369",
      "endAddress": "418 Alvarez Alley",
      "startCoords": {
        "latitude": 35.134413,
        "longitude": -106.722619
      },
      "endCoords": {
        "latitude": 35.138462,
        "longitude": -106.617763
      },
      "distanceMeters": 67566.3,
      "durationMs": 10131824,
      "drivingDurationMs": 9567998,
      "idlingDurationMs": 563826,
      "fuelConsumedMl": 8589,
      "fuelConsumedGallons": 2.269,
      "maxSpeedMph": 69.0,
      "averageSpeedMph": 14.9,
      "safetyEvents": [
        {
          "type": "speeding",
          "startMs": 1738849080000,
          "maxSpeedMph": 69.0
        }
      ]
    },
    {
      "id": "trip_44865715_20250206_006",
      "vehicleId": "44865715",
      "driverId": "20000045",
      "startMs": 1738832160000,
      "endMs": 1738850300093,
      "startAddress": "3498 Ryan Corner Suite 380",
      "endAddress": "70793 Bradley Estates Suite 241",
      "startCoords": {
        "latitude": 35.09525,
        "longitude": -106.540957
      },
      "endCoords": {
        "latitude": 35.11495,
        "longitude": -106.653893
      },
      "distanceMeters": 84922.8,
      "durationMs": 18140093,
      "drivingDurationMs": 16175226,
      "idlingDurationMs": 1964867,
      "fuelConsumedMl": 10796,
      "fuelConsumedGallons": 2.852,
      "maxSpeedMph": 40.0,
      "averageSpeedMph": 10.5,
      "safetyEvents": []
    },
    {
      "id": "trip_44865715_20250207_001",
      "vehicleId": "44865715",
      "driverId": null,
      "startMs": 1738932600000,
      "endMs": 1738937682425,
      "startAddress": "7595 Joshua Drives Suite 260",
      "endAddress": "35236 James Causeway",
      "startCoords": {
        "latitude": 35.042332,
        "longitude": -106.604603
      },
      "endCoords": {
        "latitude": 35.043991,
        "longitude": -106.628252
      },
      "distanceMeters": 37754.4,
      "durationMs": 5082425,
      "drivingDurationMs": 4525214,
      "idlingDurationMs": 557211,
      "fuelConsumedMl": 4800,
      "fuelConsumedGallons": 1.268,
      "maxSpeedMph": 53.4,
      "averageSpeedMph": 16.6,
      "safetyEvents": []
    },
    {
      "id": "trip_44865715_20250207_002",
      "vehicleId": "44865715",
      "driverId": "20000044",
      "startMs": 1738934400000,
      "endMs": 1738944806622,
      "startAddress": "5354 Thompson Fords Apt. 190",
      "endAddress": "6696 Ramos Lodge",
      "startCoords": {
        "latitude": 35.072196,
        "longitude": -106.689649
      },
      "endCoords": {
        "latitude": 35.057254,
        "longitude": -106.687589
      },
      "distanceMeters": 56290.9,
      "durationMs": 10406623,
      "drivingDurationMs": 8510105,
      "idlingDurationMs": 1896517,
      "fuelConsumedMl": 7158,
      "fuelConsumedGallons": 1.891,
      "maxSpeedMph": 47.8,
      "averageSpeedMph": 12.1,
      "safetyEvents": []
    },
    {
      "id": "trip_44865715_20250207_003",
      "vehicleId": "44865715",
      "driverId": "20000044",
      "startMs": 1738925640000,
      "endMs": 1738939742052,
      "startAddress": "791 Laurie Stravenue Apt. 510",
      "endAddress": "3254 Sierra Gardens Apt. 594",
      "startCoords": {
        "latitude": 35.063232,
        "longitude": -106.698851
      },
      "endCoords": {
        "latitude": 35.154401,
        "longitude": -106.658635
      },
      "distanceMeters": 81944.7,
      "durationMs": 14102053,
      "drivingDurationMs": 13853176,
      "idlingDurationMs": 248876,
      "fuelConsumedMl": 10417,
      "fuelConsumedGallons": 2.752,
      "maxSpeedMph": 39.0,
      "averageSpeedMph": 13.0,
      "safetyEvents": []
    },
    {
      "id": "trip_44865715_20250208_001",
      "vehicleId": "44865715",
      "driverId": null,
      "startMs": 1739034420000,
      "endMs": 1739046089104,
      "startAddress": "539 Martin Brook Apt. 917",
      "endAddress": "2805 Roach Highway Apt. 675",
      "startCoords": {
        "latitude": 35.165773,
        "longitude": -106.717728
      },
      "endCoords": {
        "latitude": 35.038855,
        "longitude": -106.60161
      },
      "distanceMeters": 81753.0,
      "durationMs": 11669104,
      "drivingDurationMs": 9962718,
      "idlingDurationMs": 1706386,
      "fuelConsumedMl": 10395,
      "fuelConsumedGallons": 2.746,
      "maxSpeedMph": 47.0,
      "averageSpeedMph": 15.7,
      "safetyEvents": []
    },
    {
      "id": "trip_44865715_20250208_002",
      "vehicleId": "44865715",
      "driverId": "20000046",
      "startMs": 1738995360000,
      "endMs": 1738997007995,
      "startAddress": "1509 Christine Trafficway",
      "endAddress": "2321 Kelsey Track Suite 712",
      "startCoords": {
        "latitude": 35.137654,
        "longitude": -106.668966
      },
      "endCoords": {
        "latitude": 35.132865,
        "longitude": -106.723871
      },
      "distanceMeters": 12056.4,
      "durationMs": 1647996,
      "drivingDurationMs": 1383425,
      "idlingDurationMs": 264570,
      "fuelConsumedMl": 1533,
      "fuelConsumedGallons": 0.405,
      "maxSpeedMph": 68.9,
      "averageSpeedMph": 16.4,
      "safetyEvents": [
        {
          "type": "speeding",
          "startMs": 1738996680000,
          "maxSpeedMph": 68.9
        }
      ]
    },
    {
      "id": "trip_44865715_20250208_003",
      "vehicleId": "44865715",
      "driverId": "20000046",
      "startMs": 1739002800000,
      "endMs": 1739004629371,
      "startAddress": "56730 Johnson River",
      "endAddress": "2181 Richard Mission Apt. 809",
      "startCoords": {
        "latitude": 35.110786,
        "longitude": -106.660666
      },
      "endCoords": {
        "latitude": 35.095325,
        "longitude": -106.631713
      },
      "distanceMeters": 8550.4,
      "durationMs": 1829372,
      "drivingDurationMs": 1513364,
      "idlingDurationMs": 316008,
      "fuelConsumedMl": 1086,
      "fuelConsumedGallons": 0.287,
      "maxSpeedMph": 33.5,
      "averageSpeedMph": 10.5,
      "safetyEvents": []
    },
    {
      "id": "trip_44865715_20250208_004",
      "vehicleId": "44865715",
      "driverId": "20000046",
      "startMs": 1739026140000,
      "endMs": 1739035350333,
      "startAddress": "134 Zhang Orchard",
      "endAddress": "2901 Donovan Summit",
      "startCoords": {
        "latitude": 35.092299,
        "longitude": -106.699988
      },
      "endCoords": {
        "latitude": 35.101849,
        "longitude": -106.631368
      },
      "distanceMeters": 60568.0,
      "durationMs": 9210334,
      "drivingDurationMs": 8772816,
      "idlingDurationMs": 437517,
      "fuelConsumedMl": 7700,
      "fuelConsumedGallons": 2.034,
      "maxSpeedMph": 44.6,
      "averageSpeedMph": 14.7,
      "safetyEvents": []
    },
    {
      "id": "trip_44865715_20250209_001",
      "vehicleId": "44865715",
      "driverId": "20000046",
      "startMs": 1739087280000,
      "endMs": 1739089399389,
      "startAddress": "53303 Henderson Rapids",
      "endAddress": "154 White Views",
      "startCoords": {
        "latitude": 35.144167,
        "longitude": -106.549794
      },
      "endCoords": {
        "latitude": 35.155798,
        "longitude": -106.692354
      },
      "distanceMeters": 10286.1,
      "durationMs": 2119389,
      "drivingDurationMs": 1716470,
      "idlingDurationMs": 402919,
      "fuelConsumedMl": 1306,
      "fuelConsumedGallons": 0.345,
      "maxSpeedMph": 31.5,
      "averageSpeedMph": 10.9,
      "safetyEvents": []
    },
    {
      "id": "trip_44865715_20250209_002",
      "vehicleId": "44865715",
      "driverId": "20000046",
      "startMs": 1739115780000,
      "endMs": 1739116721252,
      "startAddress": "4092 Barnes Roads",
      "endAddress": "776 Brittany Island",
      "startCoords": {
        "latitude": 35.066167,
        "longitude": -106.700062
      },
      "endCoords": {
        "latitude": 35.09263,
        "longitude": -106.593663
      },
      "distanceMeters": 6386.1,
      "durationMs": 941253,
      "drivingDurationMs": 754481,
      "idlingDurationMs": 186771,
      "fuelConsumedMl": 810,
      "fuelConsumedGallons": 0.214,
      "maxSpeedMph": 47.8,
      "averageSpeedMph": 15.2,
      "safetyEvents": []
    },
    {
      "id": "trip_44865715_20250209_003",
      "vehicleId": "44865715",
      "driverId": "20000046",
      "startMs": 1739104620000,
      "endMs": 1739109504543,
      "startAddress": "821 Mckenzie Ford",
      "endAddress": "57203 Travis Knolls Apt. 410",
      "startCoords": {
        "latitude": 35.114817,
        "longitude": -106.579663
      },
      "endCoords": {
        "latitude": 35.14181,
        "longitude": -106.688021
      },
      "distanceMeters": 34918.0,
      "durationMs": 4884543,
      "drivingDurationMs": 4001035,
      "idlingDurationMs": 883508,
      "fuelConsumedMl": 4440,
      "fuelConsumedGallons": 1.173,
      "maxSpeedMph": 54.9,
      "averageSpeedMph": 16.0,
      "safetyEvents": []
    },
    {
      "id": "trip_44865715_20250210_001",
      "vehicleId": "44865715",
      "driverId": "20000045",
      "startMs": 1739168160000,
      "endMs": 1739172666741,
      "startAddress": "491 Kevin Route Suite 264",
      "endAddress": "59963 Barber Motorway Suite 278",
      "startCoords": {
        "latitude": 35.164402,
        "longitude": -106.552061
      },
      "endCoords": {
        "latitude": 35.153074,
        "longitude": -106.557253
      },
      "distanceMeters": 37540.7,
      "durationMs": 4506742,
      "drivingDurationMs": 4233611,
      "idlingDurationMs": 273131,
      "fuelConsumedMl": 4773,
      "fuelConsumedGallons": 1.261,
      "maxSpeedMph": 31.4,
      "averageSpeedMph": 18.6,
      "safetyEvents": []
    },
    {
      "id": "trip_44865715_20250210_002",
      "vehicleId": "44865715",
      "driverId": "20000045",
      "startMs": 1739171100000,
      "endMs": 1739180356157,
      "startAddress": "3785 Calvin Radial Suite 588",
      "endAddress": "23022 Morgan Lock Apt. 298",
      "startCoords": {
        "latitude": 35.045613,
        "longitude": -106.596993
      },
      "endCoords": {
        "latitude": 35.165006,
        "longitude": -106.64206
      },
      "distanceMeters": 48553.3,
      "durationMs": 9256157,
      "drivingDurationMs": 7454067,
      "idlingDurationMs": 1802090,
      "fuelConsumedMl": 6174,
      "fuelConsumedGallons": 1.631,
      "maxSpeedMph": 28.7,
      "averageSpeedMph": 11.7,
      "safetyEvents": []
    },
    {
      "id": "trip_44865715_20250210_003",
      "vehicleId": "44865715",
      "driverId": "20000045",
      "startMs": 1739171520000,
      "endMs": 1739174085978,
      "startAddress": "530 Jack Lodge Apt. 535",
      "endAddress": "04513 Wagner Run Suite 014",
      "startCoords": {
        "latitude": 35.104413,
        "longitude": -106.675988
      },
      "endCoords": {
        "latitude": 35.13028,
        "longitude": -106.564276
      },
      "distanceMeters": 12708.7,
      "durationMs": 2565979,
      "drivingDurationMs": 2334047,
      "idlingDurationMs": 231931,
      "fuelConsumedMl": 1616,
      "fuelConsumedGallons": 0.427,
      "maxSpeedMph": 53.6,
      "averageSpeedMph": 11.1,
      "safetyEvents": []
    },
    {
      "id": "trip_44865715_20250211_001",
      "vehicleId": "44865715",
      "driverId": "20000044",
      "startMs": 1739282880000,
      "endMs": 1739298035047,
      "startAddress": "05670 Norris Inlet Suite 514",
      "endAddress": "3885 Gardner Locks Suite 914",
      "startCoords": {
        "latitude": 35.162751,
        "longitude": -106.640349
      },
      "endCoords": {
        "latitude": 35.078938,
        "longitude": -106.694937
      },
      "distanceMeters": 76572.6,
      "durationMs": 15155047,
      "drivingDurationMs": 12238653,
      "idlingDurationMs": 2916394,
      "fuelConsumedMl": 9736,
      "fuelConsumedGallons": 2.572,
      "maxSpeedMph": 43.9,
      "averageSpeedMph": 11.3,
      "safetyEvents": []
    },
    {
      "id": "trip_44865715_20250211_002",
      "vehicleId": "44865715",
      "driverId": "20000044",
      "startMs": 1739255880000,
      "endMs": 1739258673070,
      "startAddress": "56230 Jose Fall Apt. 512",
      "endAddress": "2749 Cole Estates",
      "startCoords": {
        "latitude": 35.133334,
        "longitude": -106.659005
      },
      "endCoords": {
        "latitude": 35.116002,
        "longitude": -106.629861
      },
      "distanceMeters": 18132.7,
      "durationMs": 2793070,
      "drivingDurationMs": 2366704,
      "idlingDurationMs": 426366,
      "fuelConsumedMl": 2305,
      "fuelConsumedGallons": 0.609,
      "maxSpeedMph": 68.0,
      "averageSpeedMph": 14.5,
      "safetyEvents": [
        {
          "type": "speeding",
          "startMs": 1739256120000,
          "maxSpeedMph": 68.0
        }
      ]
    },
    {
      "id": "trip_44865715_20250211_003",
      "vehicleId": "44865715",
      "driverId": "20000044",
      "startMs": 1739281560000,
      "endMs": 1739291321634,
      "startAddress": "79113 White Union",
      "endAddress": "36208 April Mall",
      "startCoords": {
        "latitude": 35.116744,
        "longitude": -106.594314
      },
      "endCoords": {
        "latitude": 35.062142,
        "longitude": -106.542758
      },
      "distanceMeters": 58058.2,
      "durationMs": 9761635,
      "drivingDurationMs": 8560978,
      "idlingDurationMs": 1200656,
      "fuelConsumedMl": 7382,
      "fuelConsumedGallons": 1.95,
      "maxSpeedMph": 32.0,
      "averageSpeedMph": 13.3,
      "safetyEvents": []
    },
    {
      "id": "trip_44865715_20250211_004",
      "vehicleId": "44865715",
      "driverId": "20000044",
      "startMs": 1739288640000,
      "endMs": 1739292719389,
      "startAddress": "4972 Edward Motorway",
      "endAddress": "2634 Laura Orchard Suite 640",
      "startCoords": {
        "latitude": 35.086205,
        "longitude": -106.665665
      },
      "endCoords": {
        "latitude": 35.076243,
        "longitude": -106.586269
      },
      "distanceMeters": 21480.8,
      "durationMs": 4079389,
      "drivingDurationMs": 3280234,
      "idlingDurationMs": 799155,
      "fuelConsumedMl": 2729,
      "fuelConsumedGallons": 0.721,
      "maxSpeedMph": 43.8,
      "averageSpeedMph": 11.8,
      "safetyEvents": []
    },
    {
      "id": "trip_44865715_20250211_005",
      "vehicleId": "44865715",
      "driverId": "20000044",
      "startMs": 1739276940000,
      "endMs": 1739289595357,
      "startAddress": "969 Padilla Land Suite 146",
      "endAddress": "483 Cindy Knoll",
      "startCoords": {
        "latitude": 35.129536,
        "longitude": -106.705994
      },
      "endCoords": {
        "latitude": 35.051659,
        "longitude": -106.546954
      },
      "distanceMeters": 79786.6,
      "durationMs": 12655357,
      "drivingDurationMs": 10807093,
      "idlingDurationMs": 1848264,
      "fuelConsumedMl": 10145,
      "fuelConsumedGallons": 2.68,
      "maxSpeedMph": 38.1,
      "averageSpeedMph": 14.1,
      "safetyEvents": []
    },
    {
      "id": "trip_44865715_20250211_006",
      "vehicleId": "44865715",
      "driverId": "20000044",
      "startMs": 1739263860000,
      "endMs": 1739272753826,
      "startAddress": "806 Samantha Neck Suite 835",
      "endAddress": "92429 Jennifer Path Suite 411",
      "startCoords": {
        "latitude": 35.072111,
        "longitude": -106.549588
      },
      "endCoords": {
        "latitude": 35.112249,
        "longitude": -106.601872
      },
      "distanceMeters": 45930.5,
      "durationMs": 8893827,
      "drivingDurationMs": 8499704,
      "idlingDurationMs": 394123,
      "fuelConsumedMl": 5841,
      "fuelConsumedGallons": 1.543,
      "maxSpeedMph": 62.7,
      "averageSpeedMph": 11.6,
      "safetyEvents": []
    },
    {
      "id": "trip_44865715_20250212_001",
      "vehicleId": "44865715",
      "driverId": "20000045",
      "startMs": 1739352540000,
      "endMs": 1739358224800,
      "startAddress": "6373 Cordova Extensions",
      "endAddress": "38649 Cooper Crossroad",
      "startCoords": {
        "latitude": 35.0408,
        "longitude": -106.604142
      },
      "endCoords": {
        "latitude": 35.145578,
        "longitude": -106.719908
      },
      "distanceMeters": 27355.6,
      "durationMs": 5684800,
      "drivingDurationMs": 4984783,
      "idlingDurationMs": 700017,
      "fuelConsumedMl": 3479,
      "fuelConsumedGallons": 0.919,
      "maxSpeedMph": 62.3,
      "averageSpeedMph": 10.8,
      "safetyEvents": []
    },
    {
      "id": "trip_44865715_20250212_002",
      "vehicleId": "44865715",
      "driverId": "20000045",
      "startMs": 1739383740000,
      "endMs": 1739386989730,
      "startAddress": "99949 Smith Creek",
      "endAddress": "967 Vickie Mills Suite 016",
      "startCoords": {
        "latitude": 35.131774,
        "longitude": -106.656337
      },
      "endCoords": {
        "latitude": 35.162645,
        "longitude": -106.68279
      },
      "distanceMeters": 18137.8,
      "durationMs": 3249731,
      "drivingDurationMs": 2874673,
      "idlingDurationMs": 375058,
      "fuelConsumedMl": 2305,
      "fuelConsumedGallons": 0.609,
      "maxSpeedMph": 55.4,
      "averageSpeedMph": 12.5,
      "safetyEvents": []
    },
    {
      "id": "trip_44865715_20250212_003",
      "vehicleId": "44865715",
      "driverId": "20000045",
      "startMs": 1739355720000,
      "endMs": 1739362773077,
      "startAddress": "79050 Brown Key Apt. 657",
      "endAddress": "3200 Anthony Lodge",
      "startCoords": {
        "latitude": 35.120888,
        "longitude": -106.684583
      },
      "endCoords": {
        "latitude": 35.052281,
        "longitude": -106.614794
      },
      "distanceMeters": 59049.3,
      "durationMs": 7053077,
      "drivingDurationMs": 6709549,
      "idlingDurationMs": 343529,
      "fuelConsumedMl": 7506,
      "fuelConsumedGallons": 1.983,
      "maxSpeedMph": 39.1,
      "averageSpeedMph": 18.7,
      "safetyEvents": []
    },
    {
      "id": "trip_44865715_20250212_004",
      "vehicleId": "44865715",
      "driverId": "20000045",
      "startMs": 1739375820000,
      "endMs": 1739385060010,
      "startAddress": "5828 Carol Underpass",
      "endAddress": "822 Shea Shores",
      "startCoords": {
        "latitude": 35.09444,
        "longitude": -106.622491
      },
      "endCoords": {
        "latitude": 35.137283,
        "longitude": -106.710004
      },
      "distanceMeters": 53784.2,
      "durationMs": 9240010,
      "drivingDurationMs": 8876758,
      "idlingDurationMs": 363252,
      "fuelConsumedMl": 6836,
      "fuelConsumedGallons": 1.806,
      "maxSpeedMph": 39.3,
      "averageSpeedMph": 13.0,
      "safetyEvents": []
    },
    {
      "id": "trip_44865715_20250212_005",
      "vehicleId": "44865715",
      "driverId": "20000045",
      "startMs": 1739344020000,
      "endMs": 1739346673915,
      "startAddress": "02139 Eric Inlet Apt. 556",
      "endAddress": "18465 Dorsey Path Suite 759",
      "startCoords": {
        "latitude": 35.164193,
        "longitude": -106.64331
      },
      "endCoords": {
        "latitude": 35.077411,
        "longitude": -106.558232
      },
      "distanceMeters": 13536.6,
      "durationMs": 2653916,
      "drivingDurationMs": 2440638,
      "idlingDurationMs": 213278,
      "fuelConsumedMl": 1722,
      "fuelConsumedGallons": 0.455,
      "maxSpeedMph": 47.8,
      "averageSpeedMph": 11.4,
      "safetyEvents": []
    },
    {
      "id": "trip_44865715_20250212_006",
      "vehicleId": "44865715",
      "driverId": "20000045",
      "startMs": 1739383500000,
      "endMs": 1739392488478,
      "startAddress": "7085 Katherine Trail",
      "endAddress": "50711 William Loaf Suite 106",
      "startCoords": {
        "latitude": 35.072046,
        "longitude": -106.722778
      },
      "endCoords": {
        "latitude": 35.042572,
        "longitude": -106.679742
      },
      "distanceMeters": 41164.2,
      "durationMs": 8988478,
      "drivingDurationMs": 7443744,
      "idlingDurationMs": 1544734,
      "fuelConsumedMl": 5235,
      "fuelConsumedGallons": 1.383,
      "maxSpeedMph": 56.8,
      "averageSpeedMph": 10.2,
      "safetyEvents": []
    },
    {
      "id": "trip_44865715_20250213_001",
      "vehicleId": "44865715",
      "driverId": "20000045",
      "startMs": 1739460600000,
      "endMs": 1739465316844,
      "startAddress": "24967 William Spur",
      "endAddress": "766 Lacey Park Suite 747",
      "startCoords": {
        "latitude": 35.089252,
        "longitude": -106.614854
      },
      "endCoords": {
        "latitude": 35.170135,
        "longitude": -106.682093
      },
      "distanceMeters": 22906.4,
      "durationMs": 4716844,
      "drivingDurationMs": 4430163,
      "idlingDurationMs": 286681,
      "fuelConsumedMl": 2911,
      "fuelConsumedGallons": 0.769,
      "maxSpeedMph": 64.9,
      "averageSpeedMph": 10.9,
      "safetyEvents": []
    },
    {
      "id": "trip_44865715_20250213_002",
      "vehicleId": "44865715",
      "driverId": "20000045",
      "startMs": 1739473080000,
      "endMs": 1739480400000,
      "startAddress": "0698 Arthur Walk Suite 552",
      "endAddress": "205 Tucker Canyon Suite 812",
      "startCoords": {
        "latitude": 35.044592,
        "longitude": -106.555904
      },
      "endCoords": {
        "latitude": 35.042165,
        "longitude": -106.633856
      },
      "distanceMeters": 38193.9,
      "durationMs": 7320000,
      "drivingDurationMs": 6783170,
      "idlingDurationMs": 536830,
      "fuelConsumedMl": 4857,
      "fuelConsumedGallons": 1.283,
      "maxSpeedMph": 47.0,
      "averageSpeedMph": 11.7,
      "safetyEvents": []
    },
    {
      "id": "trip_44865715_20250213_003",
      "vehicleId": "44865715",
      "driverId": "20000045",
      "startMs": 1739468760000,
      "endMs": 1739470234978,
      "startAddress": "37479 Rodriguez Village",
      "endAddress": "3145 Craig Ways",
      "startCoords": {
        "latitude": 35.124741,
        "longitude": -106.586329
      },
      "endCoords": {
        "latitude": 35.078931,
        "longitude": -106.640658
      },
      "distanceMeters": 9279.9,
      "durationMs": 1474979,
      "drivingDurationMs": 1248126,
      "idlingDurationMs": 226853,
      "fuelConsumedMl": 1181,
      "fuelConsumedGallons": 0.312,
      "maxSpeedMph": 53.0,
      "averageSpeedMph": 14.1,
      "safetyEvents": []
    },
    {
      "id": "trip_44865715_20250213_004",
      "vehicleId": "44865715",
      "driverId": "20000045",
      "startMs": 1739458140000,
      "endMs": 1739465834599,
      "startAddress": "2212 Monroe Cape",
      "endAddress": "7184 Henderson Spring",
      "startCoords": {
        "latitude": 35.04036,
        "longitude": -106.671481
      },
      "endCoords": {
        "latitude": 35.141328,
        "longitude": -106.589991
      },
      "distanceMeters": 49100.8,
      "durationMs": 7694600,
      "drivingDurationMs": 7102571,
      "idlingDurationMs": 592029,
      "fuelConsumedMl": 6242,
      "fuelConsumedGallons": 1.649,
      "maxSpeedMph": 37.2,
      "averageSpeedMph": 14.3,
      "safetyEvents": []
    },
    {
      "id": "trip_44865715_20250213_005",
      "vehicleId": "44865715",
      "driverId": "20000045",
      "startMs": 1739431200000,
      "endMs": 1739437563629,
      "startAddress": "86195 Davidson Heights",
      "endAddress": "959 James Spring",
      "startCoords": {
        "latitude": 35.17776,
        "longitude": -106.587581
      },
      "endCoords": {
        "latitude": 35.142361,
        "longitude": -106.580504
      },
      "distanceMeters": 45684.9,
      "durationMs": 6363629,
      "drivingDurationMs": 5791569,
      "idlingDurationMs": 572060,
      "fuelConsumedMl": 5807,
      "fuelConsumedGallons": 1.534,
      "maxSpeedMph": 63.8,
      "averageSpeedMph": 16.1,
      "safetyEvents": []
    },
    {
      "id": "trip_44865715_20250213_006",
      "vehicleId": "44865715",
      "driverId": "20000045",
      "startMs": 1739450340000,
      "endMs": 1739456719997,
      "startAddress": "82634 Carlos River Suite 657",
      "endAddress": "6882 Jennifer Square",
      "startCoords": {
        "latitude": 35.112305,
        "longitude": -106.545142
      },
      "endCoords": {
        "latitude": 35.049687,
        "longitude": -106.587265
      },
      "distanceMeters": 43624.9,
      "durationMs": 6379998,
      "drivingDurationMs": 5859920,
      "idlingDurationMs": 520078,
      "fuelConsumedMl": 5546,
      "fuelConsumedGallons": 1.465,
      "maxSpeedMph": 38.1,
      "averageSpeedMph": 15.3,
      "safetyEvents": []
    },
    {
      "id": "trip_44865715_20250214_001",
      "vehicleId": "44865715",
      "driverId": "20000044",
      "startMs": 1739525280000,
      "endMs": 1739527855225,
      "startAddress": "129 Williams Throughway Suite 721",
      "endAddress": "76373 Kathleen Lock Suite 655",
      "startCoords": {
        "latitude": 35.125991,
        "longitude": -106.667709
      },
      "endCoords": {
        "latitude": 35.177856,
        "longitude": -106.600978
      },
      "distanceMeters": 12311.1,
      "durationMs": 2575225,
      "drivingDurationMs": 2072225,
      "idlingDurationMs": 503001,
      "fuelConsumedMl": 1563,
      "fuelConsumedGallons": 0.413,
      "maxSpeedMph": 48.4,
      "averageSpeedMph": 10.7,
      "safetyEvents": []
    },
    {
      "id": "trip_44865715_20250214_002",
      "vehicleId": "44865715",
      "driverId": "20000044",
      "startMs": 1739533080000,
      "endMs": 1739543195630,
      "startAddress": "88323 Patrick Cove",
      "endAddress": "458 Michael Rapids Apt. 653",
      "startCoords": {
        "latitude": 35.146013,
        "longitude": -106.704452
      },
      "endCoords": {
        "latitude": 35.084326,
        "longitude": -106.665392
      },
      "distanceMeters": 69076.1,
      "durationMs": 10115630,
      "drivingDurationMs": 9692297,
      "idlingDurationMs": 423333,
      "fuelConsumedMl": 8782,
      "fuelConsumedGallons": 2.32,
      "maxSpeedMph": 42.2,
      "averageSpeedMph": 15.3,
      "safetyEvents": []
    },
    {
      "id": "trip_44865715_20250214_003",
      "vehicleId": "44865715",
      "driverId": "20000044",
      "startMs": 1739556900000,
      "endMs": 1739562716650,
      "startAddress": "536 Jason Common",
      "endAddress": "40449 Kelly Islands",
      "startCoords": {
        "latitude": 35.087364,
        "longitude": -106.597828
      },
      "endCoords": {
        "latitude": 35.072949,
        "longitude": -106.563542
      },
      "distanceMeters": 35523.1,
      "durationMs": 5816651,
      "drivingDurationMs": 5530416,
      "idlingDurationMs": 286235,
      "fuelConsumedMl": 4516,
      "fuelConsumedGallons": 1.193,
      "maxSpeedMph": 38.4,
      "averageSpeedMph": 13.7,
      "safetyEvents": []
    },
    {
      "id": "trip_44865715_20250215_001",
      "vehicleId": "44865715",
      "driverId": "20000044",
      "startMs": 1739605800000,
      "endMs": 1739616629489,
      "startAddress": "101 Ryan Meadows Apt. 506",
      "endAddress": "225 Hale Glens",
      "startCoords": {
        "latitude": 35.087564,
        "longitude": -106.609064
      },
      "endCoords": {
        "latitude": 35.10942,
        "longitude": -106.60577
      },
      "distanceMeters": 47084.9,
      "durationMs": 10829489,
      "drivingDurationMs": 9284889,
      "idlingDurationMs": 1544600,
      "fuelConsumedMl": 5985,
      "fuelConsumedGallons": 1.581,
      "maxSpeedMph": 36.3,
      "averageSpeedMph": 9.7,
      "safetyEvents": []
    },
    {
      "id": "trip_44865715_20250215_002",
      "vehicleId": "44865715",
      "driverId": "20000044",
      "startMs": 1739614380000,
      "endMs": 1739621713147,
      "startAddress": "1972 Chapman Landing Apt. 384",
      "endAddress": "537 Morton Station",
      "startCoords": {
        "latitude": 35.052236,
        "longitude": -106.640212
      },
      "endCoords": {
        "latitude": 35.084717,
        "longitude": -106.597577
      },
      "distanceMeters": 55288.8,
      "durationMs": 7333148,
      "drivingDurationMs": 6259977,
      "idlingDurationMs": 1073171,
      "fuelConsumedMl": 7030,
      "fuelConsumedGallons": 1.857,
      "maxSpeedMph": 58.5,
      "averageSpeedMph": 16.9,
      "safetyEvents": []
    },
    {
      "id": "trip_44865715_20250216_001",
      "vehicleId": "44865715",
      "driverId": "20000046",
      "startMs": 1739705760000,
      "endMs": 1739712162470,
      "startAddress": "8473 Miller Trail",
      "endAddress": "928 Lisa Stravenue",
      "startCoords": {
        "latitude": 35.151288,
        "longitude": -106.596869
      },
      "endCoords": {
        "latitude": 35.08099,
        "longitude": -106.576685
      },
      "distanceMeters": 44306.7,
      "durationMs": 6402470,
      "drivingDurationMs": 5968746,
      "idlingDurationMs": 433724,
      "fuelConsumedMl": 5633,
      "fuelConsumedGallons": 1.488,
      "maxSpeedMph": 32.6,
      "averageSpeedMph": 15.5,
      "safetyEvents": []
    },
    {
      "id": "trip_44865715_20250216_002",
      "vehicleId": "44865715",
      "driverId": "20000046",
      "startMs": 1739719800000,
      "endMs": 1739732896496,
      "startAddress": "064 Julie Parks Apt. 343",
      "endAddress": "651 Taylor Wells",
      "startCoords": {
        "latitude": 35.073634,
        "longitude": -106.561032
      },
      "endCoords": {
        "latitude": 35.174237,
        "longitude": -106.539005
      },
      "distanceMeters": 60174.7,
      "durationMs": 13096497,
      "drivingDurationMs": 11576319,
      "idlingDurationMs": 1520178,
      "fuelConsumedMl": 7650,
      "fuelConsumedGallons": 2.021,
      "maxSpeedMph": 40.5,
      "averageSpeedMph": 10.3,
      "safetyEvents": []
    },
    {
      "id": "trip_44865715_20250216_003",
      "vehicleId": "44865715",
      "driverId": "20000046",
      "startMs": 1739725860000,
      "endMs": 1739730991214,
      "startAddress": "22035 Greg Stravenue",
      "endAddress": "15414 Coleman Estates Suite 340",
      "startCoords": {
        "latitude": 35.069707,
        "longitude": -106.717657
      },
      "endCoords": {
        "latitude": 35.156294,
        "longitude": -106.699608
      },
      "distanceMeters": 24710.9,
      "durationMs": 5131215,
      "drivingDurationMs": 4356067,
      "idlingDurationMs": 775147,
      "fuelConsumedMl": 3142,
      "fuelConsumedGallons": 0.83,
      "maxSpeedMph": 68.7,
      "averageSpeedMph": 10.8,
      "safetyEvents": [
        {
          "type": "speeding",
          "startMs": 1739730300000,
          "maxSpeedMph": 68.7
        }
      ]
    },
    {
      "id": "trip_44865715_20250216_004",
      "vehicleId": "44865715",
      "driverId": "20000046",
      "startMs": 1739693580000,
      "endMs": 1739699260075,
      "startAddress": "22250 Gonzalez Skyway Suite 563",
      "endAddress": "445 Chad Station",
      "startCoords": {
        "latitude": 35.079264,
        "longitude": -106.618524
      },
      "endCoords": {
        "latitude": 35.100851,
        "longitude": -106.675748
      },
      "distanceMeters": 38707.7,
      "durationMs": 5680076,
      "drivingDurationMs": 5022146,
      "idlingDurationMs": 657930,
      "fuelConsumedMl": 4921,
      "fuelConsumedGallons": 1.3,
      "maxSpeedMph": 54.5,
      "averageSpeedMph": 15.2,
      "safetyEvents": []
    },
    {
      "id": "trip_44865715_20250217_001",
      "vehicleId": "44865715",
      "driverId": "20000045",
      "startMs": 1739815620000,
      "endMs": 1739823537864,
      "startAddress": "624 Lucas Forge Apt. 308",
      "endAddress": "5485 James Trail",
      "startCoords": {
        "latitude": 35.073314,
        "longitude": -106.667168
      },
      "endCoords": {
        "latitude": 35.182206,
        "longitude": -106.561839
      },
      "distanceMeters": 55362.9,
      "durationMs": 7917865,
      "drivingDurationMs": 7445502,
      "idlingDurationMs": 472363,
      "fuelConsumedMl": 7041,
      "fuelConsumedGallons": 1.86,
      "maxSpeedMph": 67.9,
      "averageSpeedMph": 15.6,
      "safetyEvents": [
        {
          "type": "speeding",
          "startMs": 1739817960000,
          "maxSpeedMph": 67.9
        }
      ]
    },
    {
      "id": "trip_44865715_20250217_002",
      "vehicleId": "44865715",
      "driverId": "20000045",
      "startMs": 1739802720000,
      "endMs": 1739808060800,
      "startAddress": "38165 Linda Camp Apt. 352",
      "endAddress": "4920 Mckay Garden Apt. 237",
      "startCoords": {
        "latitude": 35.053753,
        "longitude": -106.575007
      },
      "endCoords": {
        "latitude": 35.122311,
        "longitude": -106.593231
      },
      "distanceMeters": 31797.0,
      "durationMs": 5340800,
      "drivingDurationMs": 4620041,
      "idlingDurationMs": 720759,
      "fuelConsumedMl": 4043,
      "fuelConsumedGallons": 1.068,
      "maxSpeedMph": 38.9,
      "averageSpeedMph": 13.3,
      "safetyEvents": []
    },
    {
      "id": "trip_44865715_20250218_001",
      "vehicleId": "44865715",
      "driverId": "20000046",
      "startMs": 1739865660000,
      "endMs": 1739871661867,
      "startAddress": "78590 Christopher Viaduct",
      "endAddress": "837 Dennis Ways",
      "startCoords": {
        "latitude": 35.172249,
        "longitude": -106.694623
      },
      "endCoords": {
        "latitude": 35.042976,
        "longitude": -106.713248
      },
      "distanceMeters": 37432.9,
      "durationMs": 6001867,
      "drivingDurationMs": 5278457,
      "idlingDurationMs": 723410,
      "fuelConsumedMl": 4758,
      "fuelConsumedGallons": 1.257,
      "maxSpeedMph": 45.3,
      "averageSpeedMph": 14.0,
      "safetyEvents": []
    },
    {
      "id": "trip_44865715_20250218_002",
      "vehicleId": "44865715",
      "driverId": "20000046",
      "startMs": 1739873700000,
      "endMs": 1739882599873,
      "startAddress": "7315 Fox Mews Suite 413",
      "endAddress": "778 Michelle Ways Apt. 014",
      "startCoords": {
        "latitude": 35.113294,
        "longitude": -106.677071
      },
      "endCoords": {
        "latitude": 35.153936,
        "longitude": -106.680218
      },
      "distanceMeters": 58953.0,
      "durationMs": 8899874,
      "drivingDurationMs": 7353659,
      "idlingDurationMs": 1546214,
      "fuelConsumedMl": 7495,
      "fuelConsumedGallons": 1.98,
      "maxSpeedMph": 67.2,
      "averageSpeedMph": 14.8,
      "safetyEvents": [
        {
          "type": "speeding",
          "startMs": 1739875680000,
          "maxSpeedMph": 67.2
        }
      ]
    },
    {
      "id": "trip_44865715_20250218_003",
      "vehicleId": "44865715",
      "driverId": "20000046",
      "startMs": 1739883300000,
      "endMs": 1739895899468,
      "startAddress": "74303 Rebecca Junctions",
      "endAddress": "76211 Martin Spurs",
      "startCoords": {
        "latitude": 35.111137,
        "longitude": -106.627136
      },
      "endCoords": {
        "latitude": 35.041175,
        "longitude": -106.698999
      },
      "distanceMeters": 62447.3,
      "durationMs": 12599469,
      "drivingDurationMs": 10537078,
      "idlingDurationMs": 2062391,
      "fuelConsumedMl": 7938,
      "fuelConsumedGallons": 2.097,
      "maxSpeedMph": 71.9,
      "averageSpeedMph": 11.1,
      "safetyEvents": [
        {
          "type": "speeding",
          "startMs": 1739889480000,
          "maxSpeedMph": 71.9
        }
      ]
    },
    {
      "id": "trip_44865715_20250218_004",
      "vehicleId": "44865715",
      "driverId": "20000046",
      "startMs": 1739887920000,
      "endMs": 1739894710329,
      "startAddress": "375 Janet Burg",
      "endAddress": "878 Lucero View",
      "startCoords": {
        "latitude": 35.156136,
        "longitude": -106.57233
      },
      "endCoords": {
        "latitude": 35.096551,
        "longitude": -106.563677
      },
      "distanceMeters": 41198.1,
      "durationMs": 6790330,
      "drivingDurationMs": 5540003,
      "idlingDurationMs": 1250327,
      "fuelConsumedMl": 5239,
      "fuelConsumedGallons": 1.384,
      "maxSpeedMph": 39.6,
      "averageSpeedMph": 13.6,
      "safetyEvents": []
    },
    {
      "id": "trip_44865715_20250218_005",
      "vehicleId": "44865715",
      "driverId": "20000046",
      "startMs": 1739863080000,
      "endMs": 1739876457403,
      "startAddress": "092 Rodgers Street Apt. 867",
      "endAddress": "09166 Andrew Walks",
      "startCoords": {
        "latitude": 35.152008,
        "longitude": -106.658871
      },
      "endCoords": {
        "latitude": 35.124751,
        "longitude": -106.694953
      },
      "distanceMeters": 67593.8,
      "durationMs": 13377403,
      "drivingDurationMs": 10868171,
      "idlingDurationMs": 2509232,
      "fuelConsumedMl": 8593,
      "fuelConsumedGallons": 2.27,
      "maxSpeedMph": 41.6,
      "averageSpeedMph": 11.3,
      "safetyEvents": []
    },
    {
      "id": "trip_44865715_20250219_001",
      "vehicleId": "44865715",
      "driverId": "20000045",
      "startMs": 1739976360000,
      "endMs": 1739977633092,
      "startAddress": "094 Tran Track",
      "endAddress": "752 Richardson Viaduct Suite 002",
      "startCoords": {
        "latitude": 35.062623,
        "longitude": -106.693809
      },
      "endCoords": {
        "latitude": 35.109027,
        "longitude": -106.638915
      },
      "distanceMeters": 9087.4,
      "durationMs": 1273093,
      "drivingDurationMs": 1091017,
      "idlingDurationMs": 182075,
      "fuelConsumedMl": 1155,
      "fuelConsumedGallons": 0.305,
      "maxSpeedMph": 29.7,
      "averageSpeedMph": 16.0,
      "safetyEvents": []
    },
    {
      "id": "trip_44865715_20250219_002",
      "vehicleId": "44865715",
      "driverId": "20000045",
      "startMs": 1739975100000,
      "endMs": 1739992019411,
      "startAddress": "136 William Alley",
      "endAddress": "077 Becker Springs Apt. 363",
      "startCoords": {
        "latitude": 35.07159,
        "longitude": -106.718028
      },
      "endCoords": {
        "latitude": 35.156742,
        "longitude": -106.631113
      },
      "distanceMeters": 82638.9,
      "durationMs": 16919411,
      "drivingDurationMs": 13840606,
      "idlingDurationMs": 3078805,
      "fuelConsumedMl": 10508,
      "fuelConsumedGallons": 2.776,
      "maxSpeedMph": 40.6,
      "averageSpeedMph": 10.9,
      "safetyEvents": []
    },
    {
      "id": "trip_44865715_20250220_001",
      "vehicleId": "44865715",
      "driverId": "20000045",
      "startMs": 1740062520000,
      "endMs": 1740076136771,
      "startAddress": "69412 King Parkway",
      "endAddress": "57899 Alex Field",
      "startCoords": {
        "latitude": 35.14569,
        "longitude": -106.634626
      },
      "endCoords": {
        "latitude": 35.175709,
        "longitude": -106.720398
      },
      "distanceMeters": 69701.9,
      "durationMs": 13616771,
      "drivingDurationMs": 11203845,
      "idlingDurationMs": 2412926,
      "fuelConsumedMl": 8862,
      "fuelConsumedGallons": 2.341,
      "maxSpeedMph": 67.7,
      "averageSpeedMph": 11.5,
      "safetyEvents": [
        {
          "type": "speeding",
          "startMs": 1740072180000,
          "maxSpeedMph": 67.7
        }
      ]
    },
    {
      "id": "trip_44865715_20250220_002",
      "vehicleId": "44865715",
      "driverId": "20000045",
      "startMs": 1740032700000,
      "endMs": 1740044673583,
      "startAddress": "69988 Aguirre Falls",
      "endAddress": "52812 Amanda Trace",
      "startCoords": {
        "latitude": 35.058999,
        "longitude": -106.593618
      },
      "endCoords": {
        "latitude": 35.050081,
        "longitude": -106.682675
      },
      "distanceMeters": 68704.4,
      "durationMs": 11973584,
      "drivingDurationMs": 10043279,
      "idlingDurationMs": 1930304,
      "fuelConsumedMl": 8737,
      "fuelConsumedGallons": 2.308,
      "maxSpeedMph": 65.3,
      "averageSpeedMph": 12.8,
      "safetyEvents": [
        {
          "type": "speeding",
          "startMs": 1740034680000,
          "maxSpeedMph": 65.3
        }
      ]
    },
    {
      "id": "trip_44865715_20250220_003",
      "vehicleId": "44865715",
      "driverId": "20000045",
      "startMs": 1740072000000,
      "endMs": 1740076448888,
      "startAddress": "880 Duffy Springs Apt. 520",
      "endAddress": "6542 Julie Ridge",
      "startCoords": {
        "latitude": 35.038494,
        "longitude": -106.546932
      },
      "endCoords": {
        "latitude": 35.145189,
        "longitude": -106.537475
      },
      "distanceMeters": 31566.0,
      "durationMs": 4448888,
      "drivingDurationMs": 3828790,
      "idlingDurationMs": 620098,
      "fuelConsumedMl": 4013,
      "fuelConsumedGallons": 1.06,
      "maxSpeedMph": 35.2,
      "averageSpeedMph": 15.9,
      "safetyEvents": []
    },
    {
      "id": "trip_44865715_20250220_004",
      "vehicleId": "44865715",
      "driverId": "20000045",
      "startMs": 1740034260000,
      "endMs": 1740038505084,
      "startAddress": "8637 Melinda Haven Apt. 517",
      "endAddress": "214 Stokes Forges Suite 407",
      "startCoords": {
        "latitude": 35.045831,
        "longitude": -106.72379
      },
      "endCoords": {
        "latitude": 35.133653,
        "longitude": -106.586005
      },
      "distanceMeters": 25655.3,
      "durationMs": 4245084,
      "drivingDurationMs": 3492291,
      "idlingDurationMs": 752794,
      "fuelConsumedMl": 3263,
      "fuelConsumedGallons": 0.862,
      "maxSpeedMph": 52.1,
      "averageSpeedMph": 13.5,
      "safetyEvents": []
    },
    {
      "id": "trip_44865715_20250221_001",
      "vehicleId": "44865715",
      "driverId": "20000044",
      "startMs": 1740147120000,
      "endMs": 1740154083977,
      "startAddress": "52992 Lynn Course",
      "endAddress": "3493 Ramirez Glen Apt. 637",
      "startCoords": {
        "latitude": 35.152199,
        "longitude": -106.719498
      },
      "endCoords": {
        "latitude": 35.079511,
        "longitude": -106.622424
      },
      "distanceMeters": 50452.6,
      "durationMs": 6963977,
      "drivingDurationMs": 6408880,
      "idlingDurationMs": 555097,
      "fuelConsumedMl": 6416,
      "fuelConsumedGallons": 1.695,
      "maxSpeedMph": 45.7,
      "averageSpeedMph": 16.2,
      "safetyEvents": []
    },
    {
      "id": "trip_44865715_20250221_002",
      "vehicleId": "44865715",
      "driverId": "20000044",
      "startMs": 1740157080000,
      "endMs": 1740160830308,
      "startAddress": "879 Williamson Hills",
      "endAddress": "0099 Linda Square",
      "startCoords": {
        "latitude": 35.04331,
        "longitude": -106.687512
      },
      "endCoords": {
        "latitude": 35.057233,
        "longitude": -106.542206
      },
      "distanceMeters": 22977.4,
      "durationMs": 3750308,
      "drivingDurationMs": 3537543,
      "idlingDurationMs": 212765,
      "fuelConsumedMl": 2922,
      "fuelConsumedGallons": 0.772,
      "maxSpeedMph": 61.3,
      "averageSpeedMph": 13.7,
      "safetyEvents": []
    },
    {
      "id": "trip_44865715_20250221_003",
      "vehicleId": "44865715",
      "driverId": "20000044",
      "startMs": 1740129780000,
      "endMs": 1740131169008,
      "startAddress": "80443 Bryan Lights",
      "endAddress": "6460 Angela Court Suite 031",
      "startCoords": {
        "latitude": 35.147562,
        "longitude": -106.621726
      },
      "endCoords": {
        "latitude": 35.039841,
        "longitude": -106.712368
      },
      "distanceMeters": 6989.6,
      "durationMs": 1389008,
      "drivingDurationMs": 1206595,
      "idlingDurationMs": 182413,
      "fuelConsumedMl": 890,
      "fuelConsumedGallons": 0.235,
      "maxSpeedMph": 28.4,
      "averageSpeedMph": 11.3,
      "safetyEvents": []
    },
    {
      "id": "trip_44865715_20250221_004",
      "vehicleId": "44865715",
      "driverId": "20000044",
      "startMs": 1740134760000,
      "endMs": 1740136282044,
      "startAddress": "9435 Joseph Corners",
      "endAddress": "91214 Brandy View",
      "startCoords": {
        "latitude": 35.086506,
        "longitude": -106.625001
      },
      "endCoords": {
        "latitude": 35.165516,
        "longitude": -106.673989
      },
      "distanceMeters": 8963.6,
      "durationMs": 1522045,
      "drivingDurationMs": 1261392,
      "idlingDurationMs": 260653,
      "fuelConsumedMl": 1139,
      "fuelConsumedGallons": 0.301,
      "maxSpeedMph": 43.1,
      "averageSpeedMph": 13.2,
      "safetyEvents": []
    },
    {
      "id": "trip_44865715_20250222_001",
      "vehicleId": "44865715",
      "driverId": "20000046",
      "startMs": 1740211200000,
      "endMs": 1740214554623,
      "startAddress": "198 Lopez Underpass",
      "endAddress": "895 Martin Forest",
      "startCoords": {
        "latitude": 35.1613,
        "longitude": -106.666364
      },
      "endCoords": {
        "latitude": 35.079916,
        "longitude": -106.623852
      },
      "distanceMeters": 26513.2,
      "durationMs": 3354623,
      "drivingDurationMs": 3155081,
      "idlingDurationMs": 199542,
      "fuelConsumedMl": 3373,
      "fuelConsumedGallons": 0.891,
      "maxSpeedMph": 64.1,
      "averageSpeedMph": 17.7,
      "safetyEvents": []
    },
    {
      "id": "trip_44865715_20250222_002",
      "vehicleId": "44865715",
      "driverId": "20000046",
      "startMs": 1740235140000,
      "endMs": 1740245067923,
      "startAddress": "96735 Jones Cliff Apt. 601",
      "endAddress": "2222 Le Via Suite 826",
      "startCoords": {
        "latitude": 35.06315,
        "longitude": -106.576667
      },
      "endCoords": {
        "latitude": 35.094636,
        "longitude": -106.556901
      },
      "distanceMeters": 57171.2,
      "durationMs": 9927923,
      "drivingDurationMs": 7993845,
      "idlingDurationMs": 1934078,
      "fuelConsumedMl": 7268,
      "fuelConsumedGallons": 1.92,
      "maxSpeedMph": 63.6,
      "averageSpeedMph": 12.9,
      "safetyEvents": []
    },
    {
      "id": "trip_44865715_20250223_001",
      "vehicleId": "44865715",
      "driverId": "20000046",
      "startMs": 1740330180000,
      "endMs": 1740338856391,
      "startAddress": "6967 Owens Divide Apt. 296",
      "endAddress": "706 Morgan Estates Apt. 254",
      "startCoords": {
        "latitude": 35.044352,
        "longitude": -106.537587
      },
      "endCoords": {
        "latitude": 35.115261,
        "longitude": -106.551477
      },
      "distanceMeters": 43674.0,
      "durationMs": 8676391,
      "drivingDurationMs": 8335789,
      "idlingDurationMs": 340603,
      "fuelConsumedMl": 5553,
      "fuelConsumedGallons": 1.467,
      "maxSpeedMph": 56.3,
      "averageSpeedMph": 11.3,
      "safetyEvents": []
    },
    {
      "id": "trip_44865715_20250223_002",
      "vehicleId": "44865715",
      "driverId": "20000046",
      "startMs": 1740331020000,
      "endMs": 1740341427198,
      "startAddress": "8802 Travis Place",
      "endAddress": "3993 Shelby Mall",
      "startCoords": {
        "latitude": 35.088433,
        "longitude": -106.632528
      },
      "endCoords": {
        "latitude": 35.118611,
        "longitude": -106.573009
      },
      "distanceMeters": 81732.1,
      "durationMs": 10407198,
      "drivingDurationMs": 9293669,
      "idlingDurationMs": 1113530,
      "fuelConsumedMl": 10391,
      "fuelConsumedGallons": 2.745,
      "maxSpeedMph": 54.8,
      "averageSpeedMph": 17.6,
      "safetyEvents": []
    },
    {
      "id": "trip_44865715_20250223_003",
      "vehicleId": "44865715",
      "driverId": "20000046",
      "startMs": 1740325620000,
      "endMs": 1740330598563,
      "startAddress": "75134 Andrew Run Apt. 428",
      "endAddress": "837 Green Lodge Suite 533",
      "startCoords": {
        "latitude": 35.124632,
        "longitude": -106.660124
      },
      "endCoords": {
        "latitude": 35.121007,
        "longitude": -106.63626
      },
      "distanceMeters": 29939.6,
      "durationMs": 4978563,
      "drivingDurationMs": 4203029,
      "idlingDurationMs": 775534,
      "fuelConsumedMl": 3808,
      "fuelConsumedGallons": 1.006,
      "maxSpeedMph": 68.0,
      "averageSpeedMph": 13.5,
      "safetyEvents": [
        {
          "type": "speeding",
          "startMs": 1740328320000,
          "maxSpeedMph": 68.0
        }
      ]
    },
    {
      "id": "trip_44865715_20250223_004",
      "vehicleId": "44865715",
      "driverId": "20000046",
      "startMs": 1740308100000,
      "endMs": 1740319114181,
      "startAddress": "8850 Mary Station",
      "endAddress": "30279 Gavin Roads",
      "startCoords": {
        "latitude": 35.079338,
        "longitude": -106.720117
      },
      "endCoords": {
        "latitude": 35.140532,
        "longitude": -106.581058
      },
      "distanceMeters": 83375.8,
      "durationMs": 11014181,
      "drivingDurationMs": 10652408,
      "idlingDurationMs": 361773,
      "fuelConsumedMl": 10599,
      "fuelConsumedGallons": 2.8,
      "maxSpeedMph": 52.6,
      "averageSpeedMph": 16.9,
      "safetyEvents": []
    },
    {
      "id": "trip_44865715_20250224_001",
      "vehicleId": "44865715",
      "driverId": "20000044",
      "startMs": 1740398700000,
      "endMs": 1740401038644,
      "startAddress": "1365 Kaitlin Ridge Suite 681",
      "endAddress": "1789 Crawford Gateway",
      "startCoords": {
        "latitude": 35.108706,
        "longitude": -106.555665
      },
      "endCoords": {
        "latitude": 35.051953,
        "longitude": -106.536603
      },
      "distanceMeters": 14620.6,
      "durationMs": 2338644,
      "drivingDurationMs": 2049556,
      "idlingDurationMs": 289089,
      "fuelConsumedMl": 1859,
      "fuelConsumedGallons": 0.491,
      "maxSpeedMph": 64.9,
      "averageSpeedMph": 14.0,
      "safetyEvents": []
    },
    {
      "id": "trip_44865715_20250224_002",
      "vehicleId": "44865715",
      "driverId": "20000044",
      "startMs": 1740391500000,
      "endMs": 1740398179787,
      "startAddress": "467 Lori Bypass Suite 390",
      "endAddress": "75092 Silva Camp Apt. 098",
      "startCoords": {
        "latitude": 35.069824,
        "longitude": -106.683166
      },
      "endCoords": {
        "latitude": 35.163067,
        "longitude": -106.61825
      },
      "distanceMeters": 43687.6,
      "durationMs": 6679787,
      "drivingDurationMs": 5728616,
      "idlingDurationMs": 951171,
      "fuelConsumedMl": 5553,
      "fuelConsumedGallons": 1.467,
      "maxSpeedMph": 66.5,
      "averageSpeedMph": 14.6,
      "safetyEvents": [
        {
          "type": "speeding",
          "startMs": 1740392340000,
          "maxSpeedMph": 66.5
        }
      ]
    },
    {
      "id": "trip_44865715_20250224_003",
      "vehicleId": "44865715",
      "driverId": "20000044",
      "startMs": 1740415740000,
      "endMs": 1740417034152,
      "startAddress": "570 Andrea Track",
      "endAddress": "0671 Smith Rapids Apt. 498",
      "startCoords": {
        "latitude": 35.063042,
        "longitude": -106.58746
      },
      "endCoords": {
        "latitude": 35.040194,
        "longitude": -106.595435
      },
      "distanceMeters": 8075.6,
      "durationMs": 1294153,
      "drivingDurationMs": 1041934,
      "idlingDurationMs": 252219,
      "fuelConsumedMl": 1026,
      "fuelConsumedGallons": 0.271,
      "maxSpeedMph": 53.3,
      "averageSpeedMph": 14.0,
      "safetyEvents": []
    },
    {
      "id": "trip_44865715_20250225_001",
      "vehicleId": "44865715",
      "driverId": "20000045",
      "startMs": 1740484080000,
      "endMs": 1740499627676,
      "startAddress": "0302 Thompson Plains Suite 239",
      "endAddress": "059 Mclean Port Apt. 078",
      "startCoords": {
        "latitude": 35.07407,
        "longitude": -106.665102
      },
      "endCoords": {
        "latitude": 35.050759,
        "longitude": -106.560939
      },
      "distanceMeters": 82212.1,
      "durationMs": 15547676,
      "drivingDurationMs": 12456134,
      "idlingDurationMs": 3091542,
      "fuelConsumedMl": 10452,
      "fuelConsumedGallons": 2.761,
      "maxSpeedMph": 49.5,
      "averageSpeedMph": 11.8,
      "safetyEvents": []
    },
    {
      "id": "trip_44865715_20250225_002",
      "vehicleId": "44865715",
      "driverId": "20000045",
      "startMs": 1740497400000,
      "endMs": 1740505361236,
      "startAddress": "6377 Brittany Stravenue",
      "endAddress": "8624 Jennifer Heights Apt. 698",
      "startCoords": {
        "latitude": 35.159737,
        "longitude": -106.542776
      },
      "endCoords": {
        "latitude": 35.124505,
        "longitude": -106.658933
      },
      "distanceMeters": 44451.6,
      "durationMs": 7961237,
      "drivingDurationMs": 7557208,
      "idlingDurationMs": 404028,
      "fuelConsumedMl": 5652,
      "fuelConsumedGallons": 1.493,
      "maxSpeedMph": 34.2,
      "averageSpeedMph": 12.5,
      "safetyEvents": []
    },
    {
      "id": "trip_44865715_20250225_003",
      "vehicleId": "44865715",
      "driverId": "20000045",
      "startMs": 1740508200000,
      "endMs": 1740517200000,
      "startAddress": "733 Moore Road",
      "endAddress": "33884 Wu Flats Suite 946",
      "startCoords": {
        "latitude": 35.040595,
        "longitude": -106.717414
      },
      "endCoords": {
        "latitude": 35.104201,
        "longitude": -106.704109
      },
      "distanceMeters": 39452.1,
      "durationMs": 9000000,
      "drivingDurationMs": 7200000,
      "idlingDurationMs": 1800000,
      "fuelConsumedMl": 5016,
      "fuelConsumedGallons": 1.325,
      "maxSpeedMph": 68.5,
      "averageSpeedMph": 9.8,
      "safetyEvents": [
        {
          "type": "speeding",
          "startMs": 1740512880000,
          "maxSpeedMph": 68.5
        }
      ]
    },
    {
      "id": "trip_44865715_20250225_004",
      "vehicleId": "44865715",
      "driverId": "20000045",
      "startMs": 1740482640000,
      "endMs": 1740487593734,
      "startAddress": "11777 Linda Wall Suite 774",
      "endAddress": "857 Alan Rue Suite 299",
      "startCoords": {
        "latitude": 35.168593,
        "longitude": -106.619417
      },
      "endCoords": {
        "latitude": 35.053442,
        "longitude": -106.614668
      },
      "distanceMeters": 35465.9,
      "durationMs": 4953734,
      "drivingDurationMs": 4316364,
      "idlingDurationMs": 637371,
      "fuelConsumedMl": 4508,
      "fuelConsumedGallons": 1.191,
      "maxSpeedMph": 61.1,
      "averageSpeedMph": 16.0,
      "safetyEvents": []
    },
    {
      "id": "trip_44865715_20250226_001",
      "vehicleId": "44865715",
      "driverId": "20000046",
      "startMs": 1740559560000,
      "endMs": 1740564988571,
      "startAddress": "994 Lisa Village",
      "endAddress": "32613 George Islands",
      "startCoords": {
        "latitude": 35.039452,
        "longitude": -106.63933
      },
      "endCoords": {
        "latitude": 35.101803,
        "longitude": -106.670436
      },
      "distanceMeters": 25454.6,
      "durationMs": 5428572,
      "drivingDurationMs": 4350595,
      "idlingDurationMs": 1077977,
      "fuelConsumedMl": 3237,
      "fuelConsumedGallons": 0.855,
      "maxSpeedMph": 36.1,
      "averageSpeedMph": 10.5,
      "safetyEvents": []
    },
    {
      "id": "trip_44865715_20250226_002",
      "vehicleId": "44865715",
      "driverId": "20000046",
      "startMs": 1740591240000,
      "endMs": 1740598908993,
      "startAddress": "563 Thompson Plain",
      "endAddress": "169 Martinez Mount Suite 289",
      "startCoords": {
        "latitude": 35.065978,
        "longitude": -106.589858
      },
      "endCoords": {
        "latitude": 35.115184,
        "longitude": -106.672686
      },
      "distanceMeters": 55566.7,
      "durationMs": 7668993,
      "drivingDurationMs": 6583179,
      "idlingDurationMs": 1085814,
      "fuelConsumedMl": 7064,
      "fuelConsumedGallons": 1.866,
      "maxSpeedMph": 46.7,
      "averageSpeedMph": 16.2,
      "safetyEvents": []
    },
    {
      "id": "trip_44865715_20250226_003",
      "vehicleId": "44865715",
      "driverId": "20000046",
      "startMs": 1740584940000,
      "endMs": 1740593368307,
      "startAddress": "5016 Christine Port Suite 911",
      "endAddress": "31510 Williams Plaza Apt. 415",
      "startCoords": {
        "latitude": 35.051664,
        "longitude": -106.62604
      },
      "endCoords": {
        "latitude": 35.1497,
        "longitude": -106.69908
      },
      "distanceMeters": 54955.3,
      "durationMs": 8428308,
      "drivingDurationMs": 7300326,
      "idlingDurationMs": 1127982,
      "fuelConsumedMl": 6988,
      "fuelConsumedGallons": 1.846,
      "maxSpeedMph": 29.4,
      "averageSpeedMph": 14.6,
      "safetyEvents": []
    },
    {
      "id": "trip_44865715_20250226_004",
      "vehicleId": "44865715",
      "driverId": "20000046",
      "startMs": 1740571440000,
      "endMs": 1740586216985,
      "startAddress": "834 William Neck Suite 832",
      "endAddress": "95168 Garcia Plaza",
      "startCoords": {
        "latitude": 35.16299,
        "longitude": -106.664682
      },
      "endCoords": {
        "latitude": 35.124381,
        "longitude": -106.690687
      },
      "distanceMeters": 74397.8,
      "durationMs": 14776985,
      "drivingDurationMs": 12373330,
      "idlingDurationMs": 2403655,
      "fuelConsumedMl": 9460,
      "fuelConsumedGallons": 2.499,
      "maxSpeedMph": 37.7,
      "averageSpeedMph": 11.3,
      "safetyEvents": []
    },
    {
      "id": "trip_44865715_20250226_005",
      "vehicleId": "44865715",
      "driverId": "20000046",
      "startMs": 1740574920000,
      "endMs": 1740589023653,
      "startAddress": "38819 Thomas Crest",
      "endAddress": "5207 Ross Lights",
      "startCoords": {
        "latitude": 35.174077,
        "longitude": -106.688736
      },
      "endCoords": {
        "latitude": 35.087434,
        "longitude": -106.60214
      },
      "distanceMeters": 65447.4,
      "durationMs": 14103653,
      "drivingDurationMs": 12225265,
      "idlingDurationMs": 1878388,
      "fuelConsumedMl": 8320,
      "fuelConsumedGallons": 2.198,
      "maxSpeedMph": 30.2,
      "averageSpeedMph": 10.4,
      "safetyEvents": []
    },
    {
      "id": "trip_44865715_20250226_006",
      "vehicleId": "44865715",
      "driverId": null,
      "startMs": 1740566880000,
      "endMs": 1740578311296,
      "startAddress": "5281 Warner Locks Suite 617",
      "endAddress": "823 Faith Motorway",
      "startCoords": {
        "latitude": 35.125278,
        "longitude": -106.631065
      },
      "endCoords": {
        "latitude": 35.058511,
        "longitude": -106.611993
      },
      "distanceMeters": 82585.0,
      "durationMs": 11431297,
      "drivingDurationMs": 9564660,
      "idlingDurationMs": 1866637,
      "fuelConsumedMl": 10501,
      "fuelConsumedGallons": 2.774,
      "maxSpeedMph": 41.7,
      "averageSpeedMph": 16.2,
      "safetyEvents": []
    },
    {
      "id": "trip_44865715_20250227_001",
      "vehicleId": "44865715",
      "driverId": "20000044",
      "startMs": 1740658920000,
      "endMs": 1740661688525,
      "startAddress": "196 Calvin Circles",
      "endAddress": "29312 Hailey Canyon",
      "startCoords": {
        "latitude": 35.151721,
        "longitude": -106.621068
      },
      "endCoords": {
        "latitude": 35.127811,
        "longitude": -106.630885
      },
      "distanceMeters": 22637.7,
      "durationMs": 2768526,
      "drivingDurationMs": 2547798,
      "idlingDurationMs": 220728,
      "fuelConsumedMl": 2877,
      "fuelConsumedGallons": 0.76,
      "maxSpeedMph": 48.3,
      "averageSpeedMph": 18.3,
      "safetyEvents": []
    },
    {
      "id": "trip_44865715_20250227_002",
      "vehicleId": "44865715",
      "driverId": "20000044",
      "startMs": 1740663120000,
      "endMs": 1740672404624,
      "startAddress": "8139 Paul Junctions Suite 730",
      "endAddress": "401 Jean Unions Suite 967",
      "startCoords": {
        "latitude": 35.080595,
        "longitude": -106.639582
      },
      "endCoords": {
        "latitude": 35.09424,
        "longitude": -106.673256
      },
      "distanceMeters": 54449.5,
      "durationMs": 9284624,
      "drivingDurationMs": 8909894,
      "idlingDurationMs": 374731,
      "fuelConsumedMl": 6924,
      "fuelConsumedGallons": 1.829,
      "maxSpeedMph": 30.7,
      "averageSpeedMph": 13.1,
      "safetyEvents": []
    },
    {
      "id": "trip_44865715_20250228_001",
      "vehicleId": "44865715",
      "driverId": "20000046",
      "startMs": 1740760680000,
      "endMs": 1740767647756,
      "startAddress": "0052 Melissa Bridge Apt. 780",
      "endAddress": "934 Christopher Locks",
      "startCoords": {
        "latitude": 35.05663,
        "longitude": -106.619798
      },
      "endCoords": {
        "latitude": 35.093835,
        "longitude": -106.644404
      },
      "distanceMeters": 34060.8,
      "durationMs": 6967756,
      "drivingDurationMs": 6784297,
      "idlingDurationMs": 183459,
      "fuelConsumedMl": 4331,
      "fuelConsumedGallons": 1.144,
      "maxSpeedMph": 60.7,
      "averageSpeedMph": 10.9,
      "safetyEvents": []
    },
    {
      "id": "trip_44865715_20250228_002",
      "vehicleId": "44865715",
      "driverId": "20000046",
      "startMs": 1740744060000,
      "endMs": 1740759108604,
      "startAddress": "47014 Boyd Groves",
      "endAddress": "1825 Ariana Mountains Apt. 088",
      "startCoords": {
        "latitude": 35.13037,
        "longitude": -106.669964
      },
      "endCoords": {
        "latitude": 35.091667,
        "longitude": -106.607275
      },
      "distanceMeters": 74828.2,
      "durationMs": 15048605,
      "drivingDurationMs": 13416707,
      "idlingDurationMs": 1631898,
      "fuelConsumedMl": 9513,
      "fuelConsumedGallons": 2.513,
      "maxSpeedMph": 28.4,
      "averageSpeedMph": 11.1,
      "safetyEvents": []
    },
    {
      "id": "trip_44865715_20250228_003",
      "vehicleId": "44865715",
      "driverId": "20000046",
      "startMs": 1740746520000,
      "endMs": 1740753472537,
      "startAddress": "14234 Stacey Shoal Apt. 357",
      "endAddress": "5721 John Canyon Suite 879",
      "startCoords": {
        "latitude": 35.17415,
        "longitude": -106.622387
      },
      "endCoords": {
        "latitude": 35.077152,
        "longitude": -106.678198
      },
      "distanceMeters": 40812.5,
      "durationMs": 6952537,
      "drivingDurationMs": 5781112,
      "idlingDurationMs": 1171425,
      "fuelConsumedMl": 5190,
      "fuelConsumedGallons": 1.371,
      "maxSpeedMph": 40.6,
      "averageSpeedMph": 13.1,
      "safetyEvents": []
    },
    {
      "id": "trip_44865715_20250228_004",
      "vehicleId": "44865715",
      "driverId": "20000046",
      "startMs": 1740754380000,
      "endMs": 1740760786419,
      "startAddress": "8335 Nelson Wall Apt. 143",
      "endAddress": "6618 Calderon Loop",
      "startCoords": {
        "latitude": 35.102839,
        "longitude": -106.577519
      },
      "endCoords": {
        "latitude": 35.169004,
        "longitude": -106.585061
      },
      "distanceMeters": 48224.6,
      "durationMs": 6406419,
      "drivingDurationMs": 5826129,
      "idlingDurationMs": 580291,
      "fuelConsumedMl": 6132,
      "fuelConsumedGallons": 1.62,
      "maxSpeedMph": 64.0,
      "averageSpeedMph": 16.8,
      "safetyEvents": []
    }
  ]
}